Metadata-Version: 2.1
Name: distributions-bc
Version: 0.4
Summary: Gaussian and Binomial distributions
Home-page: UNKNOWN
Author: Charles Gauthey
Author-email: cjgauthey@gmail.com
License: UNKNOWN
Platform: UNKNOWN
Classifier: License :: OSI Approved :: MIT License
Requires-Python: >=3.6
